{
  "recipe": {
    "id": "classic-apple-pie",
    "title": "Classic Apple Pie",
    "description": "Traditional American dessert with flaky crust and cinnamon apples",
    "estimated_total": "PT1H30M",
    "locale": "en",
    "source": "pdf",
    "servings": 8,
    "difficulty": "Medium",
    "tags": [
      "dessert"
    ],
    "course": "dessert"
  },
  "ingredients": [
    {
      "id": "smith_apples_peeled_and_sliced",
      "name": "Smith apples, peeled and sliced",
      "quantity": 6.0,
      "unit": "Granny"
    },
    {
      "id": "sugar",
      "name": "sugar",
      "quantity": 200.0,
      "unit": "g"
    },
    {
      "id": "cinnamon",
      "name": "cinnamon",
      "quantity": 2.0,
      "unit": "tsp"
    },
    {
      "id": "shortcrust_pastry",
      "name": "shortcrust pastry",
      "quantity": 500.0,
      "unit": "g"
    },
    {
      "id": "cornstarch",
      "name": "cornstarch",
      "quantity": 1.0,
      "unit": "tbsp"
    },
    {
      "id": "juice_of_1_lemon",
      "name": "Juice of 1 lemon",
      "quantity": null,
      "unit": null
    },
    {
      "id": "1_egg_beaten",
      "name": "1 egg, beaten",
      "quantity": null,
      "unit": null
    }
  ],
  "utensils": [],
  "steps": [
    {
      "id": "preheat_oven",
      "descr": "Preheat oven to 200\u00b0C (400\u00b0F)",
      "instructions": "Preheat oven to 200\u00b0C (400\u00b0F)",
      "type": "immediate",
      "auto_start": true,
      "requires_confirm": true,
      "depends_on": [],
      "next": [
        "mix_apples"
      ],
      "on_enter": [
        {
          "say": "Right, let's preheat the oven to two hundred degrees celsius, which is about four hundred degrees fahrenheit. This will get it nice and hot for our pie."
        }
      ]
    },
    {
      "id": "mix_apples",
      "descr": "Mix apples with sugar, cinnamon, cornstarch, and lemon juice",
      "instructions": "Mix apples with sugar, cinnamon, cornstarch, and lemon juice",
      "type": "immediate",
      "auto_start": false,
      "requires_confirm": true,
      "depends_on": [
        "preheat_oven"
      ],
      "next": [
        "roll_pastry"
      ],
      "on_enter": [
        {
          "say": "Now, let's mix those lovely apples with the sugar, cinnamon, cornstarch, and a squeeze of lemon juice. Give it a good stir until everything's nicely coated."
        }
      ]
    },
    {
      "id": "roll_pastry",
      "descr": "Roll out half the pastry and line a pie dish",
      "instructions": "Roll out half the pastry and line a pie dish",
      "type": "immediate",
      "auto_start": false,
      "requires_confirm": true,
      "depends_on": [
        "mix_apples"
      ],
      "next": [
        "fill_pie"
      ],
      "on_enter": [
        {
          "say": "Let's roll out half of that lovely pastry and gently line your pie dish. Take your time to get it nice and even."
        }
      ]
    },
    {
      "id": "fill_pie",
      "descr": "Fill with apple mixture",
      "instructions": "Fill with apple mixture",
      "type": "immediate",
      "auto_start": false,
      "requires_confirm": true,
      "depends_on": [
        "roll_pastry"
      ],
      "next": [
        "cover_pie"
      ],
      "on_enter": [
        {
          "say": "Now, let's fill that pastry-lined dish with our delicious apple mixture. Spread it out evenly."
        }
      ]
    },
    {
      "id": "cover_pie",
      "descr": "Cover with remaining pastry, seal edges",
      "instructions": "Cover with remaining pastry, seal edges",
      "type": "immediate",
      "auto_start": false,
      "requires_confirm": true,
      "depends_on": [
        "fill_pie"
      ],
      "next": [
        "brush_egg"
      ],
      "on_enter": [
        {
          "say": "Time to cover the pie with the remaining pastry. Press the edges down to seal it all in. Lovely!"
        }
      ]
    },
    {
      "id": "brush_egg",
      "descr": "Brush with beaten egg, make slits for steam",
      "instructions": "Brush with beaten egg, make slits for steam",
      "type": "immediate",
      "auto_start": false,
      "requires_confirm": true,
      "depends_on": [
        "cover_pie"
      ],
      "next": [
        "bake_pie"
      ],
      "on_enter": [
        {
          "say": "Let's brush the top with that beaten egg for a beautiful golden finish. Don't forget to make a few slits for the steam to escape."
        }
      ]
    },
    {
      "id": "bake_pie",
      "descr": "Bake 45 minutes until golden, cool before serving",
      "instructions": "Bake 45 minutes until golden, cool before serving",
      "type": "timer",
      "duration": "PT45M",
      "auto_start": false,
      "requires_confirm": false,
      "depends_on": [
        "brush_egg"
      ],
      "next": [],
      "on_enter": [
        {
          "say": "Pop the pie in the oven and bake it for forty-five minutes until it's beautifully golden. Let it cool a bit before serving, if you can wait!"
        }
      ]
    }
  ],
  "events": {
    "tts_voice": "chef_friendly",
    "reminder_default": {
      "every": "PT30S"
    }
  },
  "notes": {
    "text": "Use a mix of sweet and tart apples\nChill pastry before rolling for easier handling\nServe warm with vanilla ice cream"
  }
}